pypolestar/__init__.py
pypolestar/api.py
pypolestar/auth.py
pypolestar/cli.py
pypolestar/const.py
pypolestar/exceptions.py
pypolestar/graphql.py
pypolestar/models.py
pypolestar/utils.py
pypolestar-1.9.0.dist-info/METADATA
pypolestar-1.9.0.dist-info/WHEEL
pypolestar-1.9.0.dist-info/entry_points.txt
pypolestar-1.9.0.dist-info/licenses/LICENSE
pypolestar-1.9.0.dist-info/RECORD
