Metadata-Version: 2.4
Name: pypolestar
Version: 1.9.0
Summary: Library to control Polestar
Project-URL: repository, https://github.com/pypolestar/pypolestar
Author-email:  Tuen Lee <leeyuentuen@gmail.com>, Jakob Schlyter <jakob@kirei.se>
License-Expression: MIT
License-File: LICENSE
Requires-Python: <4.0,>=3.11
Requires-Dist: gql[httpx]>=3.5.2
Requires-Dist: httpx>=0.28.1
